.gitignore
.pep8speaks.yml
.pyup.yml
.travis.yml
CONTRIBUTING.md
LICENSE
README.md
appveyor.yml
asv.conf.json
build.cmd
requirements.txt
setup.py
tox.ini
benchmarks/__init__.py
benchmarks/benchmarks.py
examples/pairwise_distance.ipynb
src/skallel_stats/__init__.py
src/skallel_stats/version.py
src/skallel_stats.egg-info/PKG-INFO
src/skallel_stats.egg-info/SOURCES.txt
src/skallel_stats.egg-info/dependency_links.txt
src/skallel_stats.egg-info/not-zip-safe
src/skallel_stats.egg-info/requires.txt
src/skallel_stats.egg-info/top_level.txt
src/skallel_stats/distance/__init__.py
src/skallel_stats/distance/api.py
src/skallel_stats/distance/cuda_backend.py
src/skallel_stats/distance/dask_backend.py
src/skallel_stats/distance/numpy_backend.py
src/skallel_stats/test/__init__.py
src/skallel_stats/test/test_api.py
src/skallel_stats/test/test_distance.py