Metadata-Version: 1.2
Name: skallel-stats
Version: 0.1.0a9
Summary: Statistical functions for genome variation data.
Home-page: https://github.com/scikit-allel/skallel-stats
Maintainer: Alistair Miles
Maintainer-email: alimanfoo@googlemail.com
License: MIT
Platform: UNKNOWN
Classifier: Development Status :: 3 - Alpha
Classifier: Intended Audience :: Developers
Classifier: Intended Audience :: Information Technology
Classifier: Intended Audience :: Science/Research
Classifier: License :: OSI Approved :: MIT License
Classifier: Programming Language :: Python
Classifier: Topic :: Software Development :: Libraries :: Python Modules
Classifier: Programming Language :: Python :: 3
Classifier: Programming Language :: Python :: 3.6
Classifier: Programming Language :: Python :: 3.7
